{
  "round": "elite-8",
  "total_games": 4,
  "completed_games": 4,
  "games": [
    { "game_number": 1, "region": "East", "team_a": "Duke", "seed_a": 1, "team_b": "UConn", "seed_b": 2, "status": "completed", "winner": "UConn" },
    { "game_number": 2, "region": "South", "team_a": "Illinois", "seed_a": 3, "team_b": "Iowa", "seed_b": 9, "status": "completed", "winner": "Illinois" },
    { "game_number": 3, "region": "West", "team_a": "Arizona", "seed_a": 1, "team_b": "Purdue", "seed_b": 2, "status": "completed", "winner": "Arizona" },
    { "game_number": 4, "region": "Midwest", "team_a": "Michigan", "seed_a": 1, "team_b": "Tennessee", "seed_b": 6, "status": "completed", "winner": "Michigan" }
  ],
  "next_game": null
}
